{"nodes": [{"id": "c_users_zarny_acs_estimates_repo_src_components_entities_offers_share_stats_dialog_tsx", "label": "share-stats-dialog.tsx", "file_type": "code", "source_file": "C:\\Users\\zarny\\acs-estimates-repo\\src\\components\\entities\\offers\\share-stats-dialog.tsx", "source_location": "L1"}, {"id": "share_stats_dialog_copytoclipboard", "label": "copyToClipboard()", "file_type": "code", "source_file": "C:\\Users\\zarny\\acs-estimates-repo\\src\\components\\entities\\offers\\share-stats-dialog.tsx", "source_location": "L83"}, {"id": "share_stats_dialog_formatdate", "label": "formatDate()", "file_type": "code", "source_file": "C:\\Users\\zarny\\acs-estimates-repo\\src\\components\\entities\\offers\\share-stats-dialog.tsx", "source_location": "L99"}, {"id": "share_stats_dialog_getdaysleft", "label": "getDaysLeft()", "file_type": "code", "source_file": "C:\\Users\\zarny\\acs-estimates-repo\\src\\components\\entities\\offers\\share-stats-dialog.tsx", "source_location": "L102"}], "edges": [{"source": "c_users_zarny_acs_estimates_repo_src_components_entities_offers_share_stats_dialog_tsx", "target": "react", "relation": "imports_from", "confidence": "EXTRACTED", "source_file": "C:\\Users\\zarny\\acs-estimates-repo\\src\\components\\entities\\offers\\share-stats-dialog.tsx", "source_location": "L3", "weight": 1.0}, {"source": "c_users_zarny_acs_estimates_repo_src_components_entities_offers_share_stats_dialog_tsx", "target": "lucide_react", "relation": "imports_from", "confidence": "EXTRACTED", "source_file": "C:\\Users\\zarny\\acs-estimates-repo\\src\\components\\entities\\offers\\share-stats-dialog.tsx", "source_location": "L4", "weight": 1.0}, {"source": "c_users_zarny_acs_estimates_repo_src_components_entities_offers_share_stats_dialog_tsx", "target": "dialog", "relation": "imports_from", "confidence": "EXTRACTED", "source_file": "C:\\Users\\zarny\\acs-estimates-repo\\src\\components\\entities\\offers\\share-stats-dialog.tsx", "source_location": "L5", "weight": 1.0}, {"source": "c_users_zarny_acs_estimates_repo_src_components_entities_offers_share_stats_dialog_tsx", "target": "button", "relation": "imports_from", "confidence": "EXTRACTED", "source_file": "C:\\Users\\zarny\\acs-estimates-repo\\src\\components\\entities\\offers\\share-stats-dialog.tsx", "source_location": "L12", "weight": 1.0}, {"source": "c_users_zarny_acs_estimates_repo_src_components_entities_offers_share_stats_dialog_tsx", "target": "alert", "relation": "imports_from", "confidence": "EXTRACTED", "source_file": "C:\\Users\\zarny\\acs-estimates-repo\\src\\components\\entities\\offers\\share-stats-dialog.tsx", "source_location": "L13", "weight": 1.0}, {"source": "c_users_zarny_acs_estimates_repo_src_components_entities_offers_share_stats_dialog_tsx", "target": "table", "relation": "imports_from", "confidence": "EXTRACTED", "source_file": "C:\\Users\\zarny\\acs-estimates-repo\\src\\components\\entities\\offers\\share-stats-dialog.tsx", "source_location": "L14", "weight": 1.0}, {"source": "c_users_zarny_acs_estimates_repo_src_components_entities_offers_share_stats_dialog_tsx", "target": "spinner", "relation": "imports_from", "confidence": "EXTRACTED", "source_file": "C:\\Users\\zarny\\acs-estimates-repo\\src\\components\\entities\\offers\\share-stats-dialog.tsx", "source_location": "L22", "weight": 1.0}, {"source": "c_users_zarny_acs_estimates_repo_src_components_entities_offers_share_stats_dialog_tsx", "target": "sonner", "relation": "imports_from", "confidence": "EXTRACTED", "source_file": "C:\\Users\\zarny\\acs-estimates-repo\\src\\components\\entities\\offers\\share-stats-dialog.tsx", "source_location": "L23", "weight": 1.0}, {"source": "c_users_zarny_acs_estimates_repo_src_components_entities_offers_share_stats_dialog_tsx", "target": "utils", "relation": "imports_from", "confidence": "EXTRACTED", "source_file": "C:\\Users\\zarny\\acs-estimates-repo\\src\\components\\entities\\offers\\share-stats-dialog.tsx", "source_location": "L24", "weight": 1.0}, {"source": "c_users_zarny_acs_estimates_repo_src_components_entities_offers_share_stats_dialog_tsx", "target": "share_stats_dialog_copytoclipboard", "relation": "contains", "confidence": "EXTRACTED", "source_file": "C:\\Users\\zarny\\acs-estimates-repo\\src\\components\\entities\\offers\\share-stats-dialog.tsx", "source_location": "L83", "weight": 1.0}, {"source": "c_users_zarny_acs_estimates_repo_src_components_entities_offers_share_stats_dialog_tsx", "target": "share_stats_dialog_formatdate", "relation": "contains", "confidence": "EXTRACTED", "source_file": "C:\\Users\\zarny\\acs-estimates-repo\\src\\components\\entities\\offers\\share-stats-dialog.tsx", "source_location": "L99", "weight": 1.0}, {"source": "c_users_zarny_acs_estimates_repo_src_components_entities_offers_share_stats_dialog_tsx", "target": "share_stats_dialog_getdaysleft", "relation": "contains", "confidence": "EXTRACTED", "source_file": "C:\\Users\\zarny\\acs-estimates-repo\\src\\components\\entities\\offers\\share-stats-dialog.tsx", "source_location": "L102", "weight": 1.0}], "raw_calls": [{"caller_nid": "share_stats_dialog_copytoclipboard", "callee": "catch", "source_file": "C:\\Users\\zarny\\acs-estimates-repo\\src\\components\\entities\\offers\\share-stats-dialog.tsx", "source_location": "L84"}, {"caller_nid": "share_stats_dialog_copytoclipboard", "callee": "then", "source_file": "C:\\Users\\zarny\\acs-estimates-repo\\src\\components\\entities\\offers\\share-stats-dialog.tsx", "source_location": "L84"}, {"caller_nid": "share_stats_dialog_copytoclipboard", "callee": "writeText", "source_file": "C:\\Users\\zarny\\acs-estimates-repo\\src\\components\\entities\\offers\\share-stats-dialog.tsx", "source_location": "L84"}, {"caller_nid": "share_stats_dialog_formatdate", "callee": "formatDateTime", "source_file": "C:\\Users\\zarny\\acs-estimates-repo\\src\\components\\entities\\offers\\share-stats-dialog.tsx", "source_location": "L99"}, {"caller_nid": "share_stats_dialog_getdaysleft", "callee": "getTime", "source_file": "C:\\Users\\zarny\\acs-estimates-repo\\src\\components\\entities\\offers\\share-stats-dialog.tsx", "source_location": "L105"}, {"caller_nid": "share_stats_dialog_getdaysleft", "callee": "getTime", "source_file": "C:\\Users\\zarny\\acs-estimates-repo\\src\\components\\entities\\offers\\share-stats-dialog.tsx", "source_location": "L105"}, {"caller_nid": "share_stats_dialog_getdaysleft", "callee": "ceil", "source_file": "C:\\Users\\zarny\\acs-estimates-repo\\src\\components\\entities\\offers\\share-stats-dialog.tsx", "source_location": "L106"}]}